compressor/__init__.py
compressor/semantic.py
compressor/minbpe/__init__.py
compressor/minbpe/base.py
compressor/minbpe/basic.py
compressor/minbpe/regex.py
compressor/resources/__init__.py
compressor/resources/en_stopwords.pkl
compressor/resources/pt_stopwords.pkl
compressor/resources/nltk_data/corpora/stopwords.zip
compressor/resources/nltk_data/corpora/wordnet.zip
compressor/resources/nltk_data/corpora/stopwords/README
compressor/resources/nltk_data/corpora/stopwords/albanian
compressor/resources/nltk_data/corpora/stopwords/arabic
compressor/resources/nltk_data/corpora/stopwords/azerbaijani
compressor/resources/nltk_data/corpora/stopwords/basque
compressor/resources/nltk_data/corpora/stopwords/belarusian
compressor/resources/nltk_data/corpora/stopwords/bengali
compressor/resources/nltk_data/corpora/stopwords/catalan
compressor/resources/nltk_data/corpora/stopwords/chinese
compressor/resources/nltk_data/corpora/stopwords/danish
compressor/resources/nltk_data/corpora/stopwords/dutch
compressor/resources/nltk_data/corpora/stopwords/english
compressor/resources/nltk_data/corpora/stopwords/finnish
compressor/resources/nltk_data/corpora/stopwords/french
compressor/resources/nltk_data/corpora/stopwords/german
compressor/resources/nltk_data/corpora/stopwords/greek
compressor/resources/nltk_data/corpora/stopwords/hebrew
compressor/resources/nltk_data/corpora/stopwords/hinglish
compressor/resources/nltk_data/corpora/stopwords/hungarian
compressor/resources/nltk_data/corpora/stopwords/indonesian
compressor/resources/nltk_data/corpora/stopwords/italian
compressor/resources/nltk_data/corpora/stopwords/kazakh
compressor/resources/nltk_data/corpora/stopwords/nepali
compressor/resources/nltk_data/corpora/stopwords/norwegian
compressor/resources/nltk_data/corpora/stopwords/portuguese
compressor/resources/nltk_data/corpora/stopwords/romanian
compressor/resources/nltk_data/corpora/stopwords/russian
compressor/resources/nltk_data/corpora/stopwords/slovene
semantic_compressor-2.42.dist-info/licenses/LICENSE
semantic_compressor-2.42.dist-info/METADATA
semantic_compressor-2.42.dist-info/WHEEL
semantic_compressor-2.42.dist-info/top_level.txt
semantic_compressor-2.42.dist-info/RECORD
