Metadata-Version: 2.4
Name: semantic_compressor
Version: 2.42
Author: Carlo Moro
Author-email: Carlo Moro <cnmoro@gmail.com>
Classifier: Programming Language :: Python :: 3
Classifier: License :: OSI Approved :: MIT License
Classifier: Operating System :: OS Independent
Requires-Python: >=3.7
License-File: LICENSE
Requires-Dist: numpy<2
Requires-Dist: nltk
Requires-Dist: scikit-learn
Requires-Dist: lingua-language-detector
Requires-Dist: model2vec
Requires-Dist: pyspellchecker
Dynamic: author
Dynamic: license-file
Dynamic: requires-python
